pygirconvt_test_son/__init__.py
pygirconvt_test_son/converter.py
pygifconvt_test_son-1.0.0.dist-info/LICENSE
pygifconvt_test_son-1.0.0.dist-info/METADATA
pygifconvt_test_son-1.0.0.dist-info/WHEEL
pygifconvt_test_son-1.0.0.dist-info/top_level.txt
pygifconvt_test_son-1.0.0.dist-info/RECORD
